{"type":"FeatureCollection","features":[{"type":"Feature","geometry":{"type":"Point","coordinates":[121.469016,31.250452]},"properties":{"published_address":"静安区芷江西路街道西藏北路新赵家宅","geocoded_address":"上海市静安区西藏北路"}},{"type":"Feature","geometry":{"type":"Point","coordinates":[121.42031,31.2766]},"properties":{"published_address":"宝山区大场镇文华苑","geocoded_address":"上海市宝山区文华苑"}},{"type":"Feature","geometry":{"type":"Point","coordinates":[121.597016,30.990492]},"properties":{"published_address":"奉贤区金汇镇梅园村","geocoded_address":"上海市奉贤区梅园村"}}]}