{"type":"FeatureCollection","features":[{"type":"Feature","geometry":{"type":"Point","coordinates":[121.461001,31.119602]},"properties":{"type":"high","town":"徐汇区","published_address":"华泾镇龙吴路2418弄华欣家园","geocoded_address":"上海市徐汇区华欣家园"}},{"type":"Feature","geometry":{"type":"Point","coordinates":[121.448745,31.126711]},"properties":{"type":"high","town":"徐汇区","published_address":"华泾镇华发路329号","geocoded_address":"上海市徐汇区华泾镇华发路329号"}},{"type":"Feature","geometry":{"type":"Point","coordinates":[121.43386,31.11837]},"properties":{"type":"high","town":"闵行区","published_address":"梅陇镇虹梅南路1526弄","geocoded_address":"上海市闵行区梅陇镇虹梅南路1526弄"}}]}