{"type":"FeatureCollection","features":[{"type":"Feature","geometry":{"type":"Point","coordinates":[121.227232,31.022778]},"properties":{"type":"high","town":"松江区","published_address":"方松街道南期昌路459弄江虹小区","geocoded_address":"上海市松江区江虹小区"}}]}