{"type":"FeatureCollection","features":[{"type":"Feature","geometry":{"type":"Point","coordinates":[121.750534,31.178803]},"properties":{"type":"medium","town":"浦东新区","published_address":"祝桥镇晚霞路551弄晨阳小区","geocoded_address":"上海市浦东新区晨阳小区"}},{"type":"Feature","geometry":{"type":"Point","coordinates":[121.616058,31.265794]},"properties":{"type":"medium","town":"浦东新区","published_address":"金桥镇永业路188弄","geocoded_address":"上海市浦东新区金桥镇永业路188弄"}},{"type":"Feature","geometry":{"type":"Point","coordinates":[121.615781,31.267454]},"properties":{"type":"medium","town":"浦东新区","published_address":"金桥镇永业路218弄","geocoded_address":"上海市浦东新区金桥镇永业路218弄"}},{"type":"Feature","geometry":{"type":"Point","coordinates":[121.395829,31.231078]},"properties":{"type":"medium","town":"普陀区","published_address":"长风新村街道金沙江路895弄","geocoded_address":"上海市普陀区长风新村街道金沙江路895弄"}}]}