{"type":"FeatureCollection","features":[{"type":"Feature","geometry":{"type":"Point","coordinates":[121.56316,31.195396]},"properties":{"type":"medium","town":"浦东新区","published_address":"陆家嘴街道上海浦东丽思卡尔顿酒店","geocoded_address":"上海市浦东新区丽思卡尔顿酒店"}},{"type":"Feature","geometry":{"type":"Point","coordinates":[121.656363,31.219462]},"properties":{"type":"medium","town":"浦东新区","published_address":"唐镇齐爱路99弄绿城玉兰花园-御园","geocoded_address":"上海市浦东新区绿城御园"}},{"type":"Feature","geometry":{"type":"Point","coordinates":[121.349267,31.178456]},"properties":{"type":"medium","town":"闵行区","published_address":"新虹街道沪青平公路249弄晟虹新景苑","geocoded_address":"上海市闵行区晟虹新景苑"}},{"type":"Feature","geometry":{"type":"Point","coordinates":[121.34799,31.168756]},"properties":{"type":"medium","town":"闵行区","published_address":"七宝镇航华二村三街坊183-211号景丽苑","geocoded_address":"上海市闵行区景丽苑"}}]}