{"type":"FeatureCollection","features":[{"type":"Feature","geometry":{"type":"Point","coordinates":[121.656363,31.219462]},"properties":{"type":"medium","town":"浦东新区","published_address":"唐镇齐爱路99弄绿城玉兰花园-御园","geocoded_address":"上海市浦东新区绿城御园"}},{"type":"Feature","geometry":{"type":"Point","coordinates":[121.593735,31.041226]},"properties":{"type":"medium","town":"浦东新区","published_address":"航头镇沪南公路5298号","geocoded_address":"上海市浦东新区航头镇沪南公路5298号"}},{"type":"Feature","geometry":{"type":"Point","coordinates":[121.496329,31.248981]},"properties":{"type":"medium","town":"虹口区","published_address":"北外滩街道旅顺路66号","geocoded_address":"上海市虹口区北外滩街道旅顺路66号"}},{"type":"Feature","geometry":{"type":"Point","coordinates":[121.388482,31.320961]},"properties":{"type":"medium","town":"宝山区","published_address":"大场镇锦秋路743号","geocoded_address":"上海市宝山区大场镇锦秋路743号"}}]}